PwnedPy/__init__.py
PwnedPy-1.0.2019.5.dist-info/LICENSE
PwnedPy-1.0.2019.5.dist-info/METADATA
PwnedPy-1.0.2019.5.dist-info/WHEEL
PwnedPy-1.0.2019.5.dist-info/top_level.txt
PwnedPy-1.0.2019.5.dist-info/RECORD
