Metadata-Version: 2.1
Name: PwnedPy
Version: 1.0.2019.5
Summary: Python Wrapper for Have I Been Pwned API
Home-page: https://github.com/navanchauhan/PwnedPy
Author: Navan Chauhan
Author-email: navanchauhan@gmail.com
License: UNKNOWN
Platform: UNKNOWN
Classifier: Programming Language :: Python :: 3
Classifier: License :: OSI Approved :: MIT License
Classifier: Operating System :: OS Independent
Requires-Dist: requests
Requires-Dist: json
